stardate/__init__.py
stardate/templatetags/__init__.py
stardate/templatetags/stardate.py
stardate/templatetags/__pycache__/__init__.cpython-310.pyc
stardate/templatetags/__pycache__/stardate.cpython-310.pyc
django_stardate_filter-0.2.dist-info/LICENSE
django_stardate_filter-0.2.dist-info/METADATA
django_stardate_filter-0.2.dist-info/WHEEL
django_stardate_filter-0.2.dist-info/top_level.txt
django_stardate_filter-0.2.dist-info/RECORD
