Metadata-Version: 2.1
Name: django-stardate-filter
Version: 0.2
Summary: A django filter to convert a date into a stardate
Home-page: https://youbee-cas.herokuapp.com
Author: Virgo STYX
Author-email: Virgo STYX <virgostyx@gmail.com>
Project-URL: Homepage, https://github.com/virgostyx/django-stardate-filter
Project-URL: Bug Tracker, https://github.com/virgostyx/django-stardate-filter/issues
Classifier: Programming Language :: Python :: 3
Classifier: License :: OSI Approved :: MIT License
Classifier: Operating System :: OS Independent
Requires-Python: >=3.7
License-File: LICENSE
Requires-Dist: Django (>=3.0)
